canaddress/__init__.py
canaddress/parser.py
canaddress-0.1.2.dist-info/LICENSE
canaddress-0.1.2.dist-info/METADATA
canaddress-0.1.2.dist-info/WHEEL
canaddress-0.1.2.dist-info/top_level.txt
canaddress-0.1.2.dist-info/RECORD
