Metadata-Version: 2.1
Name: canaddress
Version: 0.1.2
Summary: A library for cleaning and parsing addresses.
Home-page: https://github.com/avneeshchaudhary/canaddress
Author: Avneesh Chaudhary
Author-email: hey@avneeshchaudhary.com
License: MIT
Classifier: Programming Language :: Python :: 3
Classifier: License :: OSI Approved :: MIT License
Classifier: Operating System :: OS Independent
Requires-Python: >=3.6
License-File: LICENSE
Requires-Dist: pandas
Requires-Dist: openpyxl
